isage_vdb-0.1.7.2.dist-info/licenses/LICENSE
sagevdb/__init__.py
sagevdb/_sagevdb.cpython-311-x86_64-linux-gnu.so
sagevdb/libsage_db.so
sagevdb/include/sage_db/common.h
sagevdb/include/sage_db/fusion_strategies.h
sagevdb/include/sage_db/metadata_store.h
sagevdb/include/sage_db/modality_processors.h
sagevdb/include/sage_db/multimodal_fusion.h
sagevdb/include/sage_db/multimodal_sage_db.h
sagevdb/include/sage_db/query_engine.h
sagevdb/include/sage_db/sage_db.h
sagevdb/include/sage_db/vector_store.h
sagevdb/include/sage_db/anns/anns_interface.h
sagevdb/include/sage_db/anns/brute_force_plugin.h
sagevdb/include/sage_db/anns/faiss_plugin.h
sagevdb/include/sage_db/anns/flat_gpu_plugin.h
sagevdb/include/sage_db/anns/song_plugin.h
sagevdb/include/sage_db/anns/vamana_plugin.h
sagevdb/include/sage_db/anns/flat_gpu/cuda_helpers.h
sagevdb/include/sage_db/anns/song/bin_heap.hpp
sagevdb/include/sage_db/anns/song/blocked_bloomfilter.hpp
sagevdb/include/sage_db/anns/song/bloomfilter.hpp
sagevdb/include/sage_db/anns/song/config.hpp
sagevdb/include/sage_db/anns/song/cuckoofilter.hpp
sagevdb/include/sage_db/anns/song/data.hpp
sagevdb/include/sage_db/anns/song/fixhash.hpp
sagevdb/include/sage_db/anns/song/kernelgraph.cuh
sagevdb/include/sage_db/anns/song/smmh2.hpp
sagevdb/include/sage_db/anns/song/warp_astar_accelerator.cuh
sagevdb/include/sage_db/anns/vamana/distance.h
sagevdb/include/sage_db/anns/vamana/vertex.h
isage_vdb-0.1.7.2.dist-info/METADATA
isage_vdb-0.1.7.2.dist-info/WHEEL
isage_vdb-0.1.7.2.dist-info/RECORD
