Metadata-Version: 2.2
Name: isage-vdb
Version: 0.1.7.2
Summary: High-Performance Vector Database with Pluggable ANNS Architecture
Keywords: vector database,ANNS,similarity search,FAISS,embedding
Author-Email: IntelliStream Team <shuhao_zhang@hust.edu.cn>
License: MIT
Classifier: Development Status :: 3 - Alpha
Classifier: Intended Audience :: Developers
Classifier: Intended Audience :: Science/Research
Classifier: Topic :: Scientific/Engineering :: Artificial Intelligence
Classifier: Topic :: Database
Classifier: License :: OSI Approved :: MIT License
Classifier: Programming Language :: C++
Classifier: Programming Language :: Python :: 3
Classifier: Programming Language :: Python :: 3.8
Classifier: Programming Language :: Python :: 3.9
Classifier: Programming Language :: Python :: 3.10
Classifier: Programming Language :: Python :: 3.11
Classifier: Programming Language :: Python :: 3.12
Project-URL: Homepage, https://github.com/intellistream/sageVDB
Project-URL: Documentation, https://github.com/intellistream/sageVDB#readme
Project-URL: Repository, https://github.com/intellistream/sageVDB
Project-URL: Issues, https://github.com/intellistream/sageVDB/issues
Requires-Python: >=3.8
Requires-Dist: numpy>=1.19.0
Provides-Extra: dev
Requires-Dist: pytest>=7.0.0; extra == "dev"
Requires-Dist: pytest-cov; extra == "dev"
Requires-Dist: black; extra == "dev"
Requires-Dist: isort; extra == "dev"
Requires-Dist: mypy; extra == "dev"
Provides-Extra: faiss
Requires-Dist: faiss-cpu>=1.7.0; extra == "faiss"
Provides-Extra: publish
Requires-Dist: isage-pypi-publisher; extra == "publish"
